dklfm/.DS_Store
dklfm/README.md
dklfm/__init__.py
dklfm/conf/eval.yaml
dklfm/conf/train.yaml
dklfm/data/__init__.py
dklfm/data/dataset_helpers.py
dklfm/data/dklfm_dataset.py
dklfm/dklfm.ipynb
dklfm/dklfm_new.ipynb
dklfm/eval.py
dklfm/model.py
dklfm/mses.pdf
dklfm/newdklfm/f_scaler.pt
dklfm/newdklfm/real_f_scaler.pt
dklfm/newdklfm/real_y_scaler.pt
dklfm/newdklfm/y_scaler.pt
dklfm/newdklfm.py
dklfm/plotter.py
dklfm/run.py
dklfm/run_old.py
dklfm/transformer_encoder.py
dklfm/util.py
dklfm/warmup_lr_scheduler.py
dklfm-0.1.4.dist-info/METADATA
dklfm-0.1.4.dist-info/WHEEL
dklfm-0.1.4.dist-info/RECORD
