Metadata-Version: 2.1
Name: dklfm
Version: 0.1.4
Summary: 
License: MIT
Author: Jacob Moss
Author-email: cob.mossy@gmail.com
Requires-Python: >=3.11,<4.0
Classifier: License :: OSI Approved :: MIT License
Classifier: Programming Language :: Python :: 3
Classifier: Programming Language :: Python :: 3.11
Classifier: Programming Language :: Python :: 3.12
Requires-Dist: alfi (>=1.0.2,<2.0.0)
Requires-Dist: gpytorch (>=1.11,<2.0)
Requires-Dist: hydra-core (>=1.3.2,<2.0.0)
Requires-Dist: llvmlite (==0.41.0)
Requires-Dist: matplotlib (==3.7.0)
Requires-Dist: notebook (>=7.0.6,<8.0.0)
Requires-Dist: python-dotenv
Requires-Dist: pytorch-lightning (>=2.0.9.post0,<3.0.0)
Requires-Dist: scvelo (>=0.2.5)
Requires-Dist: seaborn
Requires-Dist: tensorboard (>=2.14.1,<3.0.0)
Requires-Dist: torch (>=2.1.0,<3.0.0)
Requires-Dist: tqdm
